sneed/__init__.py
Sneed-0.0.1.post0.dist-info/LICENSE
Sneed-0.0.1.post0.dist-info/METADATA
Sneed-0.0.1.post0.dist-info/WHEEL
Sneed-0.0.1.post0.dist-info/top_level.txt
Sneed-0.0.1.post0.dist-info/RECORD
