Metadata-Version: 2.1
Name: Sneed
Version: 0.0.1.post0
Summary: Formerly Chuck's
Home-page: https://github.com/technikian/sneed
Author: technician
Author-email: <mail@xxxxxxxx.com>
License: MPL
Project-URL: Source, https://github.com/technikian/sneed
Keywords: python,Sneed,assortment,various,garbage
Classifier: Development Status :: 2 - Pre-Alpha
Classifier: Intended Audience :: Developers
Classifier: License :: OSI Approved :: Mozilla Public License 2.0 (MPL 2.0)
Classifier: Programming Language :: Python :: 3
Classifier: Programming Language :: Python :: 3.6
Classifier: Programming Language :: Python :: 3.7
Classifier: Programming Language :: Python :: 3.8
Classifier: Programming Language :: Python :: 3.9
Classifier: Programming Language :: Python :: 3.10
Classifier: Programming Language :: Python :: 3.11
Classifier: Operating System :: OS Independent
Classifier: Topic :: Utilities
License-File: LICENSE
